git_upload/__init__.py
git_upload/git_upload.py
git_upload/tests/__init__.py
git_upload/tests/test_git_upload.py
git_upload-0.0.6.dist-info/DESCRIPTION.rst
git_upload-0.0.6.dist-info/METADATA
git_upload-0.0.6.dist-info/RECORD
git_upload-0.0.6.dist-info/WHEEL
git_upload-0.0.6.dist-info/entry_points.txt
git_upload-0.0.6.dist-info/metadata.json
git_upload-0.0.6.dist-info/pbr.json
git_upload-0.0.6.dist-info/top_level.txt
