Metadata-Version: 2.0
Name: git-upload
Version: 0.0.6
Summary: A tool to upload patches to a git or gerrit repository
Home-page: http://github.com/masayukig/git-upload
Author: Masayuki Igawa
Author-email: masayuki@igawa.io
License: Apache License 2.0
Platform: UNKNOWN
Classifier: Intended Audience :: Information Technology
Classifier: Intended Audience :: System Administrators
Classifier: Intended Audience :: Developers
Classifier: License :: OSI Approved :: Apache Software License
Classifier: Operating System :: POSIX :: Linux
Classifier: Programming Language :: Python
Classifier: Programming Language :: Python :: 2
Classifier: Programming Language :: Python :: 2.7
Classifier: Programming Language :: Python :: 3
Classifier: Programming Language :: Python :: 3.6
Classifier: Topic :: Software Development :: Version Control
Requires-Dist: pbr (!=2.1.0,>=2.0.0)
Requires-Dist: futures (>=3.0.0); (python_version=='2.7' or python_version=='2.6')
